{
    "name": "Burger Shot",
    "banner_txd": "foodshops",
    "banner_texture": "burger_shot",
    "trigger": {
        "x": -1193.9,
        "y": -892.7,
        "z": 13
    },
    "ped_pos": {
        "x": -1195.25,
        "y": -893.6337,
        "z": 13.3
    },
    "ped_heading": 301.9149,
    "ped_model": "csb_burgerdrug",
    "cam_pos": {
        "x": -1193.95,
        "y": -892.85,
        "z": 14.64
    },
    "cam_fov": 40,
    "menus": [
        "41fcb726-80ff-4471-9ba1-03a7e61cb1b4"
    ]
}
